hyperpyyaml/__init__.py
hyperpyyaml/core.py
HyperPyYAML-1.2.2.dist-info/LICENSE
HyperPyYAML-1.2.2.dist-info/METADATA
HyperPyYAML-1.2.2.dist-info/WHEEL
HyperPyYAML-1.2.2.dist-info/top_level.txt
HyperPyYAML-1.2.2.dist-info/RECORD
