Metadata-Version: 2.1
Name: HyperPyYAML
Version: 1.2.2
Summary: Extensions to YAML syntax for better python interaction
Home-page: https://github.com/speechbrain/HyperPyYAML
Author: Peter Plantinga, Aku Rouhe
Author-email: speechbrain@gmail.com
Classifier: Programming Language :: Python :: 3
Classifier: License :: OSI Approved :: Apache Software License
License-File: LICENSE
Requires-Dist: pyyaml>=5.1
Requires-Dist: ruamel.yaml>=0.17.28
